edhrec/__init__.py
edhrec/caching.py
edhrec/pyedhrec.py
edhrec/utils.py
pyedhrec-0.0.1.dist-info/LICENSE
pyedhrec-0.0.1.dist-info/METADATA
pyedhrec-0.0.1.dist-info/WHEEL
pyedhrec-0.0.1.dist-info/top_level.txt
pyedhrec-0.0.1.dist-info/RECORD
