Metadata-Version: 2.1
Name: pyedhrec
Version: 0.0.1
Summary: A simple package to interact with the excellent EDHRec site for Magic the Gathering
Author-email: Stainedhat <stainedhat@gmail.com>
Project-URL: Homepage, https://github.com/stainedhat/pyedhrec
Project-URL: Issues, https://github.com/stainedhat/pyedhrec/issues
Keywords: magic,mtg,edhrec,magic the gathering,edh
Classifier: Programming Language :: Python :: 3
Classifier: License :: OSI Approved :: Apache Software License
Classifier: Operating System :: OS Independent
Requires-Python: >=3.10
License-File: LICENSE
Requires-Dist: requests
